LICENSE
MANIFEST.in
README.rst
setup.py
aio_nasa_tle_loader/__init__.py
aio_nasa_tle_loader/client.py
aio_nasa_tle_loader/log.py
aio_nasa_tle_loader.egg-info/PKG-INFO
aio_nasa_tle_loader.egg-info/SOURCES.txt
aio_nasa_tle_loader.egg-info/dependency_links.txt
aio_nasa_tle_loader.egg-info/requires.txt
aio_nasa_tle_loader.egg-info/top_level.txt
examples/simple.py