Metadata-Version: 1.1
Name: aio-nasa-tle-loader
Version: 1.0.0
Summary: Small async wrapper for `nasa-tle-loader` package
Home-page: https://github.com/nkoshell/aio-nasa-tle-loader
Author: nkoshell
Author-email: nikita.koshelev@gmail.com
License: MIT
Download-URL: https://github.com/nkoshell/aio-nasa-tle-loader/archive/1.0.0.tar.gz
Platform: UNKNOWN
